abstract_open_traffic_generator/__init__.py
abstract_open_traffic_generator/api.py
abstract_open_traffic_generator/capture.py
abstract_open_traffic_generator/config.py
abstract_open_traffic_generator/control.py
abstract_open_traffic_generator/device.py
abstract_open_traffic_generator/flow.py
abstract_open_traffic_generator/flow_ipv4.py
abstract_open_traffic_generator/lag.py
abstract_open_traffic_generator/layer1.py
abstract_open_traffic_generator/port.py
abstract_open_traffic_generator/result.py
abstract_open_traffic_generator/docs/openapi.yaml
abstract_open_traffic_generator/tests/__init__.py
abstract_open_traffic_generator/tests/conftest.py
abstract_open_traffic_generator/tests/test_capture.py
abstract_open_traffic_generator/tests/test_config.py
abstract_open_traffic_generator/tests/test_devices.py
abstract_open_traffic_generator/tests/test_flow_ipv4.py
abstract_open_traffic_generator/tests/test_pfc_pause.py
abstract_open_traffic_generator/tests/test_port.py
abstract_open_traffic_generator/tests/test_port_flow.py
abstract_open_traffic_generator/tests/test_type_error.py
abstract_open_traffic_generator-0.0.69.dist-info/LICENSE
abstract_open_traffic_generator-0.0.69.dist-info/METADATA
abstract_open_traffic_generator-0.0.69.dist-info/WHEEL
abstract_open_traffic_generator-0.0.69.dist-info/top_level.txt
abstract_open_traffic_generator-0.0.69.dist-info/RECORD
