Metadata-Version: 2.1
Name: abstract-open-traffic-generator
Version: 0.0.69
Summary: The Abstract Open Traffic Generator Python Package
Home-page: https://github.com/open-traffic-generator
Author: ajbalogh
Author-email: andy.balogh@keysight.com
License: MIT
Keywords: abstract testing open traffic generator automation
Platform: UNKNOWN
Classifier: Development Status :: 1 - Planning
Classifier: Intended Audience :: Developers
Classifier: Topic :: Software Development :: Testing :: Traffic Generation
Classifier: License :: OSI Approved :: MIT License
Classifier: Programming Language :: Python :: 2.7
Classifier: Programming Language :: Python :: 3
Requires-Python: >=2.7, <4
